mcp_server.py
debug_mcp-0.1.7.dist-info/METADATA
debug_mcp-0.1.7.dist-info/WHEEL
debug_mcp-0.1.7.dist-info/entry_points.txt
debug_mcp-0.1.7.dist-info/RECORD
